vscapi/__init__.py
vscapi/_metadata.py
vscapi/lib.py
vscapi/py.typed
vscapi/structs.py
vscapi/utils.py
vscapi/vsapi.py
vscapi/vscapi.dll
vscapi/vscapi.so
vscapi/vsenums.py
vscapi/vshelper.py
vscapi-1.2.0.dist-info/LICENSE
vscapi-1.2.0.dist-info/METADATA
vscapi-1.2.0.dist-info/WHEEL
vscapi-1.2.0.dist-info/top_level.txt
vscapi-1.2.0.dist-info/RECORD
